siteprefs/__init__.py
siteprefs/admin.py
siteprefs/apps.py
siteprefs/exceptions.py
siteprefs/models.py
siteprefs/settings.py
siteprefs/signals.py
siteprefs/toolbox.py
siteprefs/utils.py
siteprefs/locale/en/LC_MESSAGES/django.po
siteprefs/locale/fr/LC_MESSAGES/django.mo
siteprefs/locale/fr/LC_MESSAGES/django.po
siteprefs/locale/pl/LC_MESSAGES/django.mo
siteprefs/locale/pl/LC_MESSAGES/django.po
siteprefs/locale/ru/LC_MESSAGES/django.mo
siteprefs/locale/ru/LC_MESSAGES/django.po
siteprefs/migrations/0001_initial.py
siteprefs/migrations/__init__.py
siteprefs/tests/__init__.py
siteprefs/tests/conftest.py
siteprefs/tests/test_basic.py
siteprefs/tests/test_utils.py
siteprefs/tests/testapp/__init__.py
siteprefs/tests/testapp/settings.py
siteprefs/tests/testapp/testmodule.py
django_siteprefs-1.2.3.dist-info/AUTHORS
django_siteprefs-1.2.3.dist-info/LICENSE
django_siteprefs-1.2.3.dist-info/METADATA
django_siteprefs-1.2.3.dist-info/WHEEL
django_siteprefs-1.2.3.dist-info/top_level.txt
django_siteprefs-1.2.3.dist-info/RECORD
